pyvallib/__init__.py
pyvallib/cfi/__init__.py
pyvallib/cfi/binomial.py
pyvallib/cfi/blackscholes.py
pyvallib/cfi/convertible_tf.py
pyvallib/cfi/montecarlo.py
pyvallib/cfi/montecarlo_correlated.py
pyvallib/dlom/__init__.py
pyvallib/dlom/chaffe.py
pyvallib/dlom/differential_put.py
pyvallib/dlom/finnerty.py
pyvallib/dlom/ghaidarov.py
pyvallib/pv/__init__.py
pyvallib/pv/discountfactor.py
pyvallib/pv/yearfrac.py
pyvallib-0.0.1.dev3.dist-info/LICENSE
pyvallib-0.0.1.dev3.dist-info/METADATA
pyvallib-0.0.1.dev3.dist-info/WHEEL
pyvallib-0.0.1.dev3.dist-info/top_level.txt
pyvallib-0.0.1.dev3.dist-info/RECORD
