Metadata-Version: 2.1
Name: pyvallib
Version: 0.0.1.dev3
Summary: A package for common valuation methodologies in Fair Value and Fair Market Value measurements.
License: MIT License
Classifier: Programming Language :: Python :: 3.10
Requires-Python: >=3.10
License-File: LICENSE
Requires-Dist: numpy>=1.24.2
Requires-Dist: pandas>=2.1.3
Requires-Dist: scipy>=1.9.3
